Workbook

Sheet README
A1: GenomeAI AgroAnimals — Финансовая модель
A3: Версия: v1.0 · Дата: 2026-05-19 · Автор: founder
A5: Структура книги:
A6: • README — этот лист (как пользоваться)
A7: • Assumptions — все исходные предположения; меняйте только здесь
A8: • Pain Matrix — 12 интервью CustDev: что подтвердилось, ущерб
A9: • Market Sizing — TAM / SAM / SOM с confidence маркировкой
A10: • Pricing — 3 тарифа, ARPU расчёт
A11: • Unit Economics — CAC, LTV, payback per scenario
A12: • P&L 3 года — revenue / COGS / OPEX / EBITDA по кварталам в 3 сценариях
A13: • Runway — burn rate, остаток средств, момент следующего раунда
A15: Принципы:
... A27: • CAC = 135 000 ₽ — target, реальный может быть 200-350k ₽ (см. 04_business_model.md §sensitivity)

Sheet Assumptions
A1: Исходные предположения (меняйте зелёные ячейки)
A3: Валюта и время
A4: Курс USD → RUB | B4: 92 | C4: Текущий курс для конвертации $ → ₽
A5: Старт операционного периода | B5: Q3 2026 | C5: Когда начинаем считать MRR
A6: Горизонт планирования | B6: 36 месяцев | C6: 12 кварталов вперёд
A8: PRICING — тарифы (₽/голову/месяц)
A9: Starter (150-300 голов) | B9: 50 | C9: ARPU = 50 × средние 225 голов = 11 250 ₽/мес = 135 000 ₽/год
A10: Growth (300-700 голов) | B10: 35 | C10: ARPU = 35 × средние 500 голов = 17 500 ₽/мес = 210 000 ₽/год
A11: Pro (700-1200 голов) | B11: 25 | C11: ARPU = 25 × средние 950 голов = 23 750 ₽/мес = 285 000 ₽/год
A12: Средневзвешенный ARPU ₽/мес | B12: 15000 | C12: Mix Starter 40% / Growth 40% / Pro 20%
A14: UNIT ECONOMICS
A15: CAC target ₽ | B15: 135000 | C15: Целевой; реальный измерим после первых сделок
A16: CAC bear ₽ | B16: 250000 | C16: Если cold outreach дорогой и нет warm leads
A17: CAC bull ₽ | B17: 80000 | C17: Если партнёрство Союзмолоко работает
A18: Gross margin % | B18: 0.78 | C18: COGS = Claude API (12%) + cloud/инфра (6%) + поддержка (4%)
A19: Annual churn % | B19: 0.12 | C19: B2B agro SaaS benchmark; B2B SMB обычно 8-20%
A20: Retention months (LTV horizon) | B20: 60 | C20: Lifetime для расчёта LTV
A21: Pilot→MRR conversion % | B21: 0.7 | C21: После 2-мес платного пилота 70% переходят в MRR
A23: SALES PRODUCTIVITY
A24: Pilots / quarter / sales FTE (base) | B24: 3 | C24: Honest для founder-led + 1 hire
A25: Pilots / quarter / sales FTE (bear) | B25: 1 | C25: Если sales motion не сработал
A26: Pilots / quarter / sales FTE (bull) | B26: 5 | C26: Если выставка + партнёрство дают inbound
A28: TEAM COSTS (₽/месяц fully-loaded)
A29: Founder | B29: 250000 | C29: Operating salary, не учитывает equity
A30: Backend engineer (M+1) | B30: 350000 | C30: Senior, fully-loaded
A31: ML engineer (M+6) | B31: 380000 | C31: Senior, fully-loaded
A32: Sales hire (M+4) | B32: 250000 | C32: Base + bonus при closing
A34: FUNDRAISING
A35: Starting cash (pre-seed) | B35: 5000000 | C35: Допущение: own + friends&family
A36: Seed round target $ | B36: 500000 | C36: =46 млн ₽ при курсе 92
A37: Seed dilution % | B37: 0.1 | C37: Standard SAFE @ ~5M pre-money

Sheet Pain Matrix
A1: Pain Matrix — Customer Discovery (12 интервью, РФ + РБ, 150-1200 голов)
A3: Методология: CustDev (Steve Blank) + JTBD (Christensen) + анализ открытых источников. Интервью 40-60 мин, структура The Mom Test.
A5: № | B5: Проблема | C5: Подтверждено N/12 | D5: Денежный ущерб (ферма 400 голов) | E5: Как решает GenomeAI | F5: MVP-приоритет
A6: 1 | B6: Фрагментация данных (4-7 систем) | C6: 12 / 12 (100%) | D6: 2,1 ч/день × 8 000 ₽/час ≈ 400 тыс. ₽/год | E6: Единый контекст + коннекторы (Селэкс/1С/DeLaval) | F6: MVP
A7: 2 | B7: Узнаём о проблеме поздно (мастит, охота) | C7: 10 / 12 (83%) | D7: +1 500-5 000 ₽/случай мастита; 158 тыс. ₽/год | E7: Сканер инсайтов + AI приоритизация | F7: MVP
A8: 3 | B8: Субъективная выбраковка «на глаз» | C8: 9 / 12 (75%) | D8: 80-120 тыс. ₽/ошибочное решение | E8: NPV-калькулятор (Wood + survival + 8 health) | F8: Roadmap M3
A9: 4 | B9: Зависимость от конкретного зоотехника | C9: 11 / 12 (92%) | D9: -10-25% efficiency при смене (раз в 3 года) | E9: Лента событий = память хозяйства | F9: MVP
A10: 5 | B10: Нет оценки влияния решений | C10: 8 / 12 (67%) | D10: 100-500 тыс. ₽/год на повторных ошибках | E10: Анализ влияния (before/after + diff-in-diff) | F10: Roadmap M6+
A13: JTBD — что наняли GenomeAI делать (из интервью)
A14: J1 (функциональная) | B14: Когда я начинаю утро как зоотехник, я хочу за 5 минут увидеть всех проблемных коров с приоритетом, чтобы не тратить 2 часа на склейку данных из 5 систем
A15: J2 (функциональная) | B15: Когда я думаю про выбраковку, я хочу понимать сколько эта корова стоит в деньгах, чтобы не ошибиться на 100k ₽
A16: J3 (социальная) | B16: Когда у меня сменился зоотехник, я хочу чтобы новый видел всю историю стада, чтобы не терять 6 месяцев и 20% efficiency
A17: J4 (функциональная) | B17: Когда я меняю рацион или протокол, я хочу через месяц увидеть, сработало ли — иначе принимаю решения вслепую
A18: J5 (эмоциональная) | B18: Когда я уезжаю в отпуск, я хочу спать спокойно, что хозяйство не развалится без меня

Sheet Market Sizing
A1: Market Sizing — РФ + РБ молочный SaaS
A3: Confidence: 🟢 устоявшийся факт · 🟡 estimate · 🔴 assumption. Источники в 03_market_sizing.md.
A5: Контекст рынка РФ
A6: Поголовье КРС всего, голов | B6: 17200000 | C6: 🟢 | D6: Росстат
A7: Поголовье молочных коров, голов | B7: 7300000 | C7: 🟢 | D7: Союзмолоко, Росстат
A8: Производство сырого молока, тонн/год | B8: 33000000 | C8: 🟢 | D8: Минсельхоз
A9: Доля СХО в молочном стаде | B9: 0.47 | C9: 🟢 | D9: Росстат
A10: Доля КФХ | B10: 0.12 | C10: 🟢 | D10: Росстат
A11: Доля ЛПХ (не наш TAM) | B11: 0.41 | C11: 🟢 | D11: Росстат
A12: Беларусь: поголовье молочных коров | B12: 1400000 | C12: 🟢 | D12: Минсельхоз РБ
A14: TAM / SAM / SOM расчёт
A15: Хозяйств 150-1200 голов (СХО+КФХ) РФ+РБ | B15: 6800 | C15: 🟡
A16: ARPU средний, ₽/год (=Assumptions!B12 × 12) | B16: =Assumptions!B12*12
A17: TAM = ферм × ARPU | B17: =B15*B16
A18: Фильтр: интернет на ферме | B18: 0.85
A19: Фильтр: готовы рассматривать SaaS | B19: 0.95
A20: Фильтр: decision-maker доступен | B20: 0.8
A21: SAM = TAM × все фильтры | B21: =B17*B18*B19*B20
A22: SOM Y3 при 4-5% захвате SAM (base) | B22: =B21*0.045

Sheet Pricing
A1: Pricing tiers (формулы ссылаются на Assumptions)
A3: Tier | B3: Размер фермы (голов) | C3: ₽/голову/мес | D3: Среднее ARPU/мес ₽ | E3: Среднее ARPU/год ₽
A4: Starter | B4: 150-300 | C4: =Assumptions!B9 | D4: =C4*225 | E4: =D4*12
A5: Growth | B5: 300-700 | C5: =Assumptions!B10 | D5: =C5*500 | E5: =D5*12
A6: Pro | B6: 700-1200 | C6: =Assumptions!B11 | D6: =C6*950 | E6: =D6*12
A8: Mix-weighted ARPU (Starter 40% / Growth 40% / Pro 20%) | D8: =D4*0.4+D5*0.4+D6*0.2 | E8: =D8*12

Sheet Unit Economics
A1: Unit Economics — 3 сценария
A3: Метрика | B3: Bear | C3: Base | D3: Bull
A4: ARPU ₽/год (из Pricing!D8 × 12) | B4: =Pricing!E8*0.85 | C4: =Pricing!E8 | D4: =Pricing!E8*1.15
A5: Gross margin % | B5: =Assumptions!B19 | C5: =Assumptions!B19 | D5: =Assumptions!B19
A6: Gross profit ₽/год/customer | B6: =B4*B5 | C6: =C4*C5 | D6: =D4*D5
A7: CAC ₽ | B7: =Assumptions!B17 | C7: =Assumptions!B16 | D7: =Assumptions!B18
A8: Annual churn % | B8: =Assumptions!B20 | C8: =Assumptions!B20 | D8: =Assumptions!B20
A9: Avg retention months | B9: =Assumptions!B21 | C9: =Assumptions!B21 | D9: =Assumptions!B21
A10: LTV ₽ (= GP × retention/12) | B10: =B6*B9/12 | C10: =C6*C9/12 | D10: =D6*D9/12
A11: LTV/CAC ratio | B11: =B10/B7 | C11: =C10/C7 | D11: =D10/D7
A12: Payback months (CAC / monthly GP) | B12: =B7/(B6/12) | C12: =C7/(C6/12) | D12: =D7/(D6/12)

Sheet P&L 3Y
A1: P&L по кварталам Q3-2026 → Q4-2029 (12 кварталов)
A3: BASE SCENARIO (Pilots/Q/FTE=3)
A4: Метрика | B4: Q3'26 | C4: Q4'26 | D4: Q1'27 | E4: Q2'27 | F4: Q3'27 | G4: Q4'27 | H4: Q1'28 | I4: Q2'28 | J4: Q3'28 | K4: Q4'28 | L4: Q1'29 | M4: Q2'29
A5: Новые customers/Q | B5: 1 | C5: 2 | D5: 3 | E5: 3 | F5: 4 | G5: 4 | H5: 5 | I5: 5 | J5: 5 | K5: 6 | L5: 6 | M5: 6
A6: Cumulative customers (with churn) | B6: =B5 | C6: =B6*(1-Assumptions!$B$20/4)+C5 | D6: =C6*(1-Assumptions!$B$20/4)+D5 | E6: =D6*(1-Assumptions!$B$20/4)+E5 | F6: =E6*(1-Assumptions!$B$20/4)+F5 | G6: =F6*(1-Assumptions!$B$20/4)+G5 | H6: =G6*(1-Assumptions!$B$20/4)+H5 | I6: =H6*(1-Assumptions!$B$20/4)+I5 | J6: =I6*(1-Assumptions!$B$20/4)+J5 | ... M6: =L6*(1-Assumptions!$B$20/4)+M5
A7: ARR ₽ | B7: =B6*Pricing!$E$8 | C7: =C6*Pricing!$E$8 | D7: =D6*Pricing!$E$8 | E7: =E6*Pricing!$E$8 | F7: =F6*Pricing!$E$8 | G7: =G6*Pricing!$E$8 | H7: =H6*Pricing!$E$8 | I7: =I6*Pricing!$E$8 | ... M7: =M6*Pricing!$E$8
A8: Quarterly revenue ₽ | B8: =B7/4 | C8: =C7/4 | D8: =D7/4 | E8: =E7/4 | F8: =F7/4 | G8: =G7/4 | H8: =H7/4 | I8: =I7/4 | ... M8: =M7/4
A9: COGS ₽ (= revenue × (1-GM)) | B9: =B8*(1-Assumptions!$B$19) | C9: =C8*(1-Assumptions!$B$19) | D9: =D8*(1-Assumptions!$B$19) | E9: =E8*(1-Assumptions!$B$19) | F9: =F8*(1-Assumptions!$B$19) | G9: =G8*(1-Assumptions!$B$19) | H9: =H8*(1-Assumptions!$B$19) | I9: =I8*(1-Assumptions!$B$19) | ... M9: =M8*(1-Assumptions!$B$19)
A10: Gross profit ₽ | B10: =B8-B9 | C10: =C8-C9 | D10: =D8-D9 | E10: =E8-E9 | F10: =F8-F9 | G10: =G8-G9 | H10: =H8-H9 | I10: =I8-I9 | ... M10: =M8-M9
A12: Sales ₽ (CAC × new + Sales hire salary) | B12: =B5*Assumptions!$B$16+0 | C12: =C5*Assumptions!$B$16+0 | D12: =D5*Assumptions!$B$16+Assumptions!$B$30*3 | E12: =E5*Assumptions!$B$16+Assumptions!$B$30*3 | F12: =F5*Assumptions!$B$16+Assumptions!$B$30*3 | G12: =G5*Assumptions!$B$16+Assumptions!$B$30*3 | H12: =H5*Assumptions!$B$16+Assumptions!$B$30*3 | I12: =I5*Assumptions!$B$16+Assumptions!$B$30*3 | J12: =J5*Assumptions!$B$16+Assumptions!$B$30*3 | K12: =K5*Assumptions!$B$16+Assumptions!$B$30*3 | ... M12: =M5*Assumptions!$B$16+Assumptions!$B$30*3
A13: R&D ₽ (Founder+BE+ML salaries) | B13: =Assumptions!$B$27*3+Assumptions!$B$28*3 | C13: =Assumptions!$B$27*3+Assumptions!$B$28*3 | D13: =Assumptions!$B$27*3+Assumptions!$B$28*3 | E13: =Assumptions!$B$27*3+Assumptions!$B$28*3 | F13: =Assumptions!$B$27*3+Assumptions!$B$28*3 | G13: =Assumptions!$B$27*3+Assumptions!$B$28*3+Assumptions!$B$29*3 | H13: =Assumptions!$B$27*3+Assumptions!$B$28*3+Assumptions!$B$29*3 | I13: =Assumptions!$B$27*3+Assumptions!$B$28*3+Assumptions!$B$29*3 | J13: =Assumptions!$B$27*3+Assumptions!$B$28*3+Assumptions!$B$29*3 | K13: =Assumptions!$B$27*3+Assumptions!$B$28*3+Assumptions!$B$29*3 | L13: =Assumptions!$B$27*3+Assumptions!$B$28*3+Assumptions!$B$29*3 | M13: =Assumptions!$B$27*3+Assumptions!$B$28*3+Assumptions!$B$29*3
A14: G&A ₽ (~20% of total OPEX) | B14: =(B12+B13)*0.25 | C14: =(C12+C13)*0.25 | D14: =(D12+D13)*0.25 | E14: =(E12+E13)*0.25 | F14: =(F12+F13)*0.25 | G14: =(G12+G13)*0.25 | H14: =(H12+H13)*0.25 | I14: =(I12+I13)*0.25 | ... M14: =(M12+M13)*0.25
A15: Total OPEX ₽ | B15: =B12+B13+B14 | C15: =C12+C13+C14 | D15: =D12+D13+D14 | E15: =E12+E13+E14 | F15: =F12+F13+F14 | G15: =G12+G13+G14 | H15: =H12+H13+H14 | I15: =I12+I13+I14 | ... M15: =M12+M13+M14
A17: EBITDA ₽ | B17: =B10-B15 | C17: =C10-C15 | D17: =D10-D15 | E17: =E10-E15 | F17: =F10-F15 | G17: =G10-G15 | H17: =H10-H15 | I17: =I10-I15 | ... M17: =M10-M15
A19: Годовой итог EBITDA
A20: 2026 (H2) | B20: =B17+C17
A21: 2027 | B21: =D17+E17+F17+G17
A22: 2028 | B22: =H17+I17+J17+K17

Sheet Runway
A1: Runway — cash on hand + ask
A3: Cash positions
A4: Pre-seed cash | B4: =Assumptions!B33 | C4: Friends&family + own
A5: Seed round $ → ₽ | B5: =Assumptions!B34*Assumptions!B4 | C5: $500k × курс
A6: Total available cash | B6: =B4+B5 | C6: Before burn
A8: Burn analysis
A9: Cumulative burn 2026 H2 | B9: =-'P&L 3Y'!B20 | C9: Из P&L 3Y
A10: Cumulative burn 2027 | B10: =-'P&L 3Y'!B21
A11: Cumulative burn 2028 | B11: =-'P&L 3Y'!B22
A12: Total burn до Q4'28 | B12: =B9+B10+B11
A13: Cash остаток к концу 2028 года | B13: =B6-B12
A15: Use of seed funds
A16: Sales & Marketing 50% | B16: =B5*0.5
A17: Product (engineering) 30% | B17: =B5*0.3
A18: G&A + legal + reserve 20% | B18: =B5*0.2
A19: Сумма (проверка) | B19: =B16+B17+B18
